<SoDead>
	<append xpath="/progression/perks" >


	<perk name="perkMasterCraftsman" parent="skillCraftsmanship" max_level="5" name_key="perkMasterCraftsmanName" desc_key="perkMasterCraftsmanDesc" icon="ui_game_symbol_workbench"  cost_multiplier_per_level="2">
		<level_requirements level="1"><requirement name="ProgressionLevel" progression_name="attIntellect" operation="GTE" value="10" desc_key="reqIntellectLevel10"/></level_requirements>
		<level_requirements level="2"><requirement name="ProgressionLevel" progression_name="attIntellect" operation="GTE" value="10" desc_key="reqGenericPoints04"/></level_requirements>
		<level_requirements level="3"><requirement name="ProgressionLevel" progression_name="attIntellect" operation="GTE" value="10" desc_key="reqGenericPoints08"/></level_requirements>
		<level_requirements level="4"><requirement name="ProgressionLevel" progression_name="attIntellect" operation="GTE" value="10" desc_key="reqGenericPoints16"/></level_requirements>
		<level_requirements level="5"><requirement name="ProgressionLevel" progression_name="attIntellect" operation="GTE" value="10" desc_key="reqGenericPoints32"/></level_requirements>

		<effect_group>			
			<passive_effect name="CraftingTier" operation="base_add" level="5" value="5" tags="perkMasterCraftsman,perkBoomstick,perkDeadEye,perkDemolitionsExpert,perkJavelinMaster,perkSalvageOperations,perkPummelPete,perkSkullCrusher,perkMiner69r,perkBrawler,perkMachineGunner,perkHeavyArmor,perkArchery,perkGunslinger,perkDeepCuts,perkLightArmor,perkElectrocutioner,perkTurrets,perkYeahScience"/>
		
		
		</effect_group>
		
	</perk> 
	
	</append >
</SoDead>